shoeboxpy/__init__.py
shoeboxpy/animate.py
shoeboxpy/model3dof.py
shoeboxpy/model6dof.py
shoeboxpy/utils.py
shoeboxpy-0.0.2.dist-info/licenses/LICENSE
shoeboxpy-0.0.2.dist-info/METADATA
shoeboxpy-0.0.2.dist-info/WHEEL
shoeboxpy-0.0.2.dist-info/top_level.txt
shoeboxpy-0.0.2.dist-info/RECORD
