Metadata-Version: 2.4
Name: shoeboxpy
Version: 0.0.2
Summary: A shoebox approximation for a marine hydrodynamics model
Author-email: Emir Cem Gezer <me@emircem.com>
License:                       EUROPEAN UNION PUBLIC LICENCE v. 1.2
Project-URL: Homepage, https://github.com/incebellipipo/shoeboxpy
Project-URL: Repository, https://github.com/incebellipipo/shoeboxpy.git
Project-URL: Documentation, https://incebellipipo.github.io/shoeboxpy/
Project-URL: Issues, https://github.com/incebellipipo/shoeboxpy/issues
Project-URL: Source, https://github.com/incebellipipo/shoeboxpy
Keywords: hydrodynamics,marine,simulation,dynamics,vessel
Classifier: Programming Language :: Python :: 3
Classifier: Programming Language :: Python :: 3 :: Only
Classifier: Programming Language :: Python :: 3.9
Classifier: Programming Language :: Python :: 3.10
Classifier: Programming Language :: Python :: 3.11
Classifier: Programming Language :: Python :: 3.12
Classifier: Programming Language :: Python :: 3.13
Classifier: License :: OSI Approved :: European Union Public Licence 1.2 (EUPL 1.2)
Classifier: Intended Audience :: Science/Research
Classifier: Topic :: Scientific/Engineering
Classifier: Topic :: Scientific/Engineering :: Physics
Classifier: Operating System :: OS Independent
Requires-Python: >=3.9
License-File: LICENSE
Requires-Dist: numpy
Requires-Dist: scipy
Requires-Dist: matplotlib
Dynamic: license-file
